playwright_recaptcha/__init__.py
playwright_recaptcha/errors.py
playwright_recaptcha/recaptchav2/__init__.py
playwright_recaptcha/recaptchav2/async_solver.py
playwright_recaptcha/recaptchav2/base_solver.py
playwright_recaptcha/recaptchav2/recaptcha_box.py
playwright_recaptcha/recaptchav2/sync_solver.py
playwright_recaptcha/recaptchav2/translations.py
playwright_recaptcha/recaptchav3/__init__.py
playwright_recaptcha/recaptchav3/async_solver.py
playwright_recaptcha/recaptchav3/base_solver.py
playwright_recaptcha/recaptchav3/sync_solver.py
playwright_recaptcha-0.5.1.dist-info/LICENSE
playwright_recaptcha-0.5.1.dist-info/METADATA
playwright_recaptcha-0.5.1.dist-info/WHEEL
playwright_recaptcha-0.5.1.dist-info/top_level.txt
playwright_recaptcha-0.5.1.dist-info/RECORD
