Metadata-Version: 2.1
Name: playwright-recaptcha
Version: 0.5.1
Summary: A library for solving reCAPTCHA v2 and v3 with Playwright
Home-page: https://github.com/Xewdy444/Playwright-reCAPTCHA
Author: Xewdy444
Author-email: xewdy@xewdy.systems
License: MIT
Classifier: Programming Language :: Python :: 3
Classifier: Programming Language :: Python :: 3.8
Classifier: Programming Language :: Python :: 3.9
Classifier: Programming Language :: Python :: 3.10
Classifier: Programming Language :: Python :: 3.11
Classifier: Programming Language :: Python :: 3.12
Classifier: License :: OSI Approved :: MIT License
Classifier: Operating System :: OS Independent
Classifier: Intended Audience :: Developers
Classifier: Topic :: Software Development :: Testing
Classifier: Topic :: Internet :: WWW/HTTP :: Browsers
Classifier: Framework :: AsyncIO
Requires-Python: >=3.8
License-File: LICENSE
Requires-Dist: playwright >=1.33.0
Requires-Dist: pydub ==0.25.1
Requires-Dist: SpeechRecognition ==3.10.4
Requires-Dist: tenacity ==8.3.0
